{"name": "Finnick", "level": 2, "race": "Halfling", "height": "3", "weight": "65", "movement_speed": "25", "active_movement_debuffs": "None", "active_movement_speed": 15, "ST": 8, "active_ST": 8, "DX": 16, "active_DX": 16, "CN": 13, "active_CN": 13, "CH": 14, "active_CH": 14, "IN": 9, "active_IN": 10, "WP": 10, "active_WP": 9, "encumbrance_penalty_explained": "-10 being Lightly Encumbered", "gold": 7, "silver": 2, "copper": 1, "vitality_points_dice_rolls": ["6"], "vitality_points": 8, "active_vitality_points": 8, "max_vitality_points": 8, "wound_points": 13, "active_wound_points": 13, "max_wound_points": 13, "passive_perception": 12, "traits": ["none"], "proficiencies": ["none", {"proficiency_name": "Trial 1", "proficiency_description": "Probanbdo si funcioan"}, {"proficiency_name": "Prueba2", "proficiency_description": "Probanbdo nuevamente"}, {"proficiency_name": "Streetsmars", "proficiency_description": "A"}], "inventory": [{"item_name": "Black Dagger", "units": 1, "weight_per_unit": 2.0, "total_weight": 2.0, "additional_info": "From Sylas", "is_armor": false, "ac_value": null, "dx_modifier": null, "modifiers": null, "conditions": null}, {"item_name": "Dagger", "units": 1, "weight_per_unit": 1.0, "total_weight": 1.0, "additional_info": "Nothing Special"}, {"item_name": "Leather Armor", "units": 1, "weight_per_unit": 5.0, "total_weight": 5.0, "additional_info": "", "is_armor": true, "ac_value": "12", "dx_modifier": true, "modifiers": "", "conditions": ""}, {"item_name": "Leather Armor with Dex", "units": 1, "weight_per_unit": 5.0, "total_weight": 5.0, "additional_info": "1", "is_armor": true, "ac_value": "12", "dx_modifier": true, "modifiers": "", "conditions": ""}, {"item_name": "Round Shield", "units": 1, "weight_per_unit": 2.0, "total_weight": 2.0, "additional_info": "", "is_armor": false, "ac_value": null, "dx_modifier": null, "modifiers": null, "conditions": null}, {"item_name": "Leather Armor NO DEX", "units": 1, "weight_per_unit": 1.0, "total_weight": 1.0, "additional_info": "", "is_armor": true, "ac_value": "12", "dx_modifier": false, "modifiers": "", "conditions": ""}], "injury_fatigue": 0, "exhaustion": 0, "encumbrance": 2, "active_abilities": ["none"], "injury_fatigue_debuffs": "None", "on_the_ground": [{"item_name": "Winter Clothes", "units": 1, "weight_per_unit": 1.0, "total_weight": 1.0, "additional_info": "Set of Fancy Winter Clothes", "is_armor": true, "ac_value": "12", "dx_modifier": true, "modifiers": "+1", "conditions": "Almost New"}], "house_inventory": [{"item_name": "Bolts", "units": 1, "weight_per_unit": 2.0, "total_weight": 2.0, "additional_info": "1"}, {"item_name": "Leather Armor", "units": 1, "weight_per_unit": 2.0, "total_weight": 2.0, "additional_info": "Cool Looking Armor", "is_armor": true, "ac_value": "14", "dx_modifier": false, "modifiers": "1", "conditions": "Advantage on Stealth Checks"}, {"item_name": "Vestiido de Cristina", "units": 1, "weight_per_unit": 1.0, "total_weight": 1.0, "additional_info": "Un hermoso vestido", "is_armor": true, "ac_value": "15", "dx_modifier": true, "modifiers": "+2", "conditions": ""}], "ST_modifier": -1, "DX_modifier": 3, "CN_modifier": 1, "CH_modifier": 2, "IN_modifier": 0, "WP_modifier": -1, "total_ac": 17, "extra_injury_fatigue": 0, "temp_armor_modifier": 0, "armor": {"name": "Leather Armor with Dex", "ac_value": 12, "modifier": 0, "dx_modifier": true, "conditions": ""}, "shield_equipped": true, "debuffs": [{"name": "debuff_height", "value": 5}, {"name": "debuff_st", "value": -1}]}